README.md
setup.py
cs_sender/__init__.py
cs_sender/api.py
cs_sender/core.py
cs_sender/extension.py
cs_sender/log.py
cs_sender/monitor.py
cs_sender/stats.py
cs_sender.egg-info/PKG-INFO
cs_sender.egg-info/SOURCES.txt
cs_sender.egg-info/dependency_links.txt
cs_sender.egg-info/requires.txt
cs_sender.egg-info/top_level.txt